package/Imagery.py
package/__init__.py
Imagery-0.0.2.dist-info/LICENSE
Imagery-0.0.2.dist-info/METADATA
Imagery-0.0.2.dist-info/WHEEL
Imagery-0.0.2.dist-info/top_level.txt
Imagery-0.0.2.dist-info/RECORD
